{
  "project_info": {
    "project_number": "512519628593",
    "firebase_url": "https://incochat-511c9.firebaseio.com",
    "project_id": "incochat-511c9",
    "storage_bucket": "incochat-511c9.appspot.com"
  },
  "client": [
    {
      "client_info": {
        "mobilesdk_app_id": "1:512519628593:android:48f64d637e6a6e66",
        "android_client_info": {
          "package_name": "com.incochat.incochat1"
        }
      },
      "oauth_client": [
        {
          "client_id": "512519628593-f5uk9cear3fr2pvv7q1mjvh5mdvvka9u.apps.googleusercontent.com",
          "client_type": 1,
          "android_info": {
            "package_name": "com.incochat.incochat1",
            "certificate_hash": "be0f91a39394872dc6a933904fcf552bb6c9f6f9"
          }
        },
        {
          "client_id": "512519628593-hketcq9plq07i47k6q88l91dte30ck47.apps.googleusercontent.com",
          "client_type": 3
        },
        {
          "client_id": "512519628593-hketcq9plq07i47k6q88l91dte30ck47.apps.googleusercontent.com",
          "client_type": 3
        }
      ],
      "api_key": [
        {
          "current_key": "AIzaSyAoGyWqQtiA176aycOhzzpxoT3Y53EhJz8"
        }
      ],
      "services": {
        "analytics_service": {
          "status": 1
        },
        "appinvite_service": {
          "status": 2,
          "other_platform_oauth_client": [
            {
              "client_id": "512519628593-hketcq9plq07i47k6q88l91dte30ck47.apps.googleusercontent.com",
              "client_type": 3
            }
          ]
        },
        "ads_service": {
          "status": 2
        }
      }
    }
  ],
  "configuration_version": "1"
}